ndx_multichannel_volume/__init__.py
ndx_multichannel_volume/ndx_multichannel_volume.py
ndx_multichannel_volume/spec/ndx-multichannel-volume.extensions.yaml
ndx_multichannel_volume/spec/ndx-multichannel-volume.namespace.yaml
ndx_multichannel_volume-0.1.12.dist-info/LICENSE.txt
ndx_multichannel_volume-0.1.12.dist-info/METADATA
ndx_multichannel_volume-0.1.12.dist-info/WHEEL
ndx_multichannel_volume-0.1.12.dist-info/top_level.txt
ndx_multichannel_volume-0.1.12.dist-info/RECORD
