Metadata-Version: 2.1
Name: ndx-multichannel-volume
Version: 0.1.12
Summary: extension to allow use of multichannel volumetric images
Home-page: 
Author: Daniel Sprague
Author-email: daniel.sprague@ucsf.edu
License: BSD-3
Keywords: NeurodataWithoutBorders,NWB,nwb-extension,ndx-extension
Classifier: Intended Audience :: Developers
Classifier: Intended Audience :: Science/Research
Classifier: License :: OSI Approved :: BSD License
License-File: LICENSE.txt
Requires-Dist: pynwb (<3,>=1.5.0)
Requires-Dist: hdmf (<4,>=2.5.6)
